weiboa/__init__.py
weiboa/weibo.py
weiboa-0.0.2.dist-info/METADATA
weiboa-0.0.2.dist-info/WHEEL
weiboa-0.0.2.dist-info/top_level.txt
weiboa-0.0.2.dist-info/RECORD
