Metadata-Version: 2.1
Name: weiboa
Version: 0.0.2
Summary: 采集微博某话题所有微博，某条微博所有评论 https://github.com/thunderhit/weiboa
Home-page: https://github.com/thunderhit/weiboa
Author: 大邓
Author-email: thunderhit@qq.com
License: MIT
Keywords: data collect,数据采集,微博,weibo
Platform: UNKNOWN
Requires-Python: >=3.5
Requires-Dist: requests
